charla/__about__.py
charla/__init__.py
charla/chat.py
charla/cli.py
charla/config.py
charla/ui.py
charla/client/__init__.py
charla/client/github.py
charla/client/ollama.py
charla-3.0.0.dist-info/METADATA
charla-3.0.0.dist-info/WHEEL
charla-3.0.0.dist-info/entry_points.txt
charla-3.0.0.dist-info/licenses/LICENSE.txt
charla-3.0.0.dist-info/RECORD
