Metadata-Version: 2.4
Name: charla
Version: 3.0.0
Summary: A terminal based chat application that works with language models.
Project-URL: Documentation, https://github.com/yaph/charla#readme
Project-URL: Issues, https://github.com/yaph/charla/issues
Project-URL: Source, https://github.com/yaph/charla
Author-email: Ramiro Gómez <code@ramiro.org>
License-Expression: MIT
License-File: LICENSE.txt
Keywords: chat-client,chatbot,chatgpt,cli,github models,llama,llm,ollama,terminal
Classifier: Development Status :: 4 - Beta
Classifier: Programming Language :: Python
Classifier: Programming Language :: Python :: 3.10
Classifier: Programming Language :: Python :: 3.11
Classifier: Programming Language :: Python :: 3.12
Classifier: Programming Language :: Python :: Implementation :: CPython
Classifier: Programming Language :: Python :: Implementation :: PyPy
Requires-Python: >=3.10
Requires-Dist: azure-ai-inference
Requires-Dist: html2text
Requires-Dist: httpx
Requires-Dist: markdown
Requires-Dist: ollama>=0.6
Requires-Dist: platformdirs
Requires-Dist: prompt-toolkit
